dataconfy/__init__.py
dataconfy/base.py
dataconfy/env_vars.py
dataconfy/managers.py
dataconfy/serializers.py
dataconfy-0.0.1.dist-info/licenses/LICENSE
dataconfy-0.0.1.dist-info/WHEEL
dataconfy-0.0.1.dist-info/METADATA
dataconfy-0.0.1.dist-info/RECORD
