Metadata-Version: 2.4
Name: dataconfy
Version: 0.0.1
Summary: Type-safe configuration and data persistence using Python dataclasses with YAML/JSON serialization, XDG directory conventions, and environment variable support.
Author: Luca Bello
Author-email: Luca Bello <lusgabello@gmail.com>
License-File: LICENSE
Requires-Dist: platformdirs>=4.5.0
Requires-Dist: pyyaml>=6.0.3
Requires-Dist: vulture>=2.14
Requires-Python: >=3.10
Project-URL: Homepage, https://github.com/lucabello/dataconfy
Project-URL: Repository, https://github.com/lucabello/dataconfy
Project-URL: Issues, https://github.com/lucabello/dataconfy/issues
